fivempy/Server.py
fivempy/__init__.py
fivempy-0.2.6.dist-info/LICENSE
fivempy-0.2.6.dist-info/METADATA
fivempy-0.2.6.dist-info/WHEEL
fivempy-0.2.6.dist-info/top_level.txt
fivempy-0.2.6.dist-info/RECORD
