Metadata-Version: 2.1
Name: fivempy
Version: 0.2.6
Summary: A python wrapper for FiveM
Home-page: https://github.com/itasli/fivempy
Author: itasli
Author-email: ilyas.tasli@outlook.com
License: UNKNOWN
Platform: UNKNOWN
Classifier: Programming Language :: Python :: 3
Classifier: License :: OSI Approved :: MIT License
Classifier: Operating System :: OS Independent
Requires-Python: >=3.6
License-File: LICENSE
